[
  {
    "id": "4uicc0bzh",
    "name": "ゆりかもめ新橋駅前",
    "image": "https://image.xinu.ink/pic/data/115/images/4uicc0bzh-1734272655567.jpg",
    "ep": 35,
    "geo": [
      35.6655,
      139.7595
    ],
    "origin": "Google Maps",
    "originURL": "https://www.google.com/maps/d/viewer?mid=11_PeKeHQmnFUU8PNuG_1yICZW5I&ll=35.665586%2C139.75958&z=17"
  },
  {
    "id": "4uicc0c34",
    "name": "first　kitchen",
    "image": "https://image.xinu.ink/pic/data/115/images/4uicc0c34-1734186992183.jpg",
    "ep": 30,
    "geo": [
      35.6887,
      139.6986
    ],
    "origin": "Google Maps",
    "originURL": "https://www.google.com/maps/d/viewer?mid=11_PeKeHQmnFUU8PNuG_1yICZW5I&ll=35.688731%2C139.698619&z=17"
  },
  {
    "id": "4uicc0ble",
    "name": "ヒッチハイクした場所",
    "image": "https://image.xinu.ink/pic/data/115/images/4uicc0ble-1734187020447.jpg",
    "ep": 30,
    "geo": [
      35.6883,
      139.6986
    ],
    "origin": "Google Maps",
    "originURL": "https://www.google.com/maps/d/viewer?mid=11_PeKeHQmnFUU8PNuG_1yICZW5I&ll=35.688371%2C139.698664&z=17"
  },
  {
    "id": "4uicc0bgf",
    "name": "東京タワー",
    "image": "https://image.xinu.ink/pic/data/115/images/4uicc0bgf-1734187047412.jpg",
    "ep": 32,
    "geo": [
      35.6585,
      139.7454
    ],
    "origin": "Google Maps",
    "originURL": "https://www.google.com/maps/d/viewer?mid=11_PeKeHQmnFUU8PNuG_1yICZW5I&ll=35.658582%2C139.745439&z=17"
  },
  {
    "id": "4uicc0bhf",
    "cn": "自由女神像",
    "name": "女神の像",
    "image": "https://image.xinu.ink/pic/data/115/images/4uicc0bhf-1734770958185.jpg",
    "ep": 53,
    "s": null,
    "geo": [
      40.6892,
      -74.0446
    ],
    "origin": "Google Maps",
    "originURL": "https://www.google.com/maps/d/viewer?mid=11_PeKeHQmnFUU8PNuG_1yICZW5I&ll=40.689238%2C-74.044515&z=17"
  },
  {
    "id": "4uicc0bw1",
    "name": "凱旋門",
    "image": "https://image.xinu.ink/pic/data/115/images/4uicc0bw1-1734770979914.jpg",
    "ep": 53,
    "geo": [
      48.8737,
      2.2948
    ],
    "origin": "Google Maps",
    "originURL": "https://www.google.com/maps/d/viewer?mid=11_PeKeHQmnFUU8PNuG_1yICZW5I&ll=48.873778%2C2.294812&z=17"
  },
  {
    "id": "4uicc0bfq",
    "name": "赤の広場",
    "image": "https://image.xinu.ink/pic/data/115/images/4uicc0bfq-1734771002505.jpg",
    "ep": 53,
    "geo": [
      55.7539,
      37.6208
    ],
    "origin": "Google Maps",
    "originURL": "https://www.google.com/maps/d/viewer?mid=11_PeKeHQmnFUU8PNuG_1yICZW5I&ll=55.753914%2C37.620825&z=17"
  },
  {
    "id": "4uicc0bo1",
    "name": "忠犬ハチ公像",
    "image": "https://image.xinu.ink/pic/data/115/images/4uicc0bo1-1733827681503.jpg",
    "ep": 33,
    "geo": [
      35.659,
      139.7005
    ],
    "origin": "Google Maps",
    "originURL": "https://www.google.com/maps/d/viewer?mid=11_PeKeHQmnFUU8PNuG_1yICZW5I&ll=35.659052%2C139.700579&z=17"
  },
  {
    "id": "4uicc0bso",
    "name": "１０９付近渋谷駅出口",
    "image": "https://image.xinu.ink/pic/data/115/images/4uicc0bso-1734187135142.jpg",
    "ep": 33,
    "geo": [
      35.6596,
      139.699
    ],
    "origin": "Google Maps",
    "originURL": "https://www.google.com/maps/d/viewer?mid=11_PeKeHQmnFUU8PNuG_1yICZW5I&ll=35.65963%2C139.699022&z=17"
  },
  {
    "id": "4uicc0bj2",
    "cn": "西班牙坂",
    "name": "スペイン坂",
    "image": "https://image.xinu.ink/pic/data/115/images/4uicc0bj2-1733827856428.jpg",
    "ep": 33,
    "geo": [
      35.6615,
      139.6988
    ],
    "origin": "Google Maps",
    "originURL": "https://www.google.com/maps/d/viewer?mid=11_PeKeHQmnFUU8PNuG_1yICZW5I&ll=35.661545%2C139.698839&z=17"
  },
  {
    "id": "4uicc0bsx",
    "name": "東急ハンズ",
    "image": "https://image.xinu.ink/pic/data/115/images/4uicc0bsx-1734187176916.jpg",
    "ep": 33,
    "geo": [
      35.6621,
      139.6974
    ],
    "origin": "Google Maps",
    "originURL": "https://www.google.com/maps/d/viewer?mid=11_PeKeHQmnFUU8PNuG_1yICZW5I&ll=35.662145%2C139.697468&z=17"
  },
  {
    "id": "4uicc0bdm",
    "name": "parco",
    "image": "https://image.xinu.ink/pic/data/115/images/4uicc0bdm-1734187198236.jpg",
    "ep": 33,
    "geo": [
      35.662,
      139.6989
    ],
    "origin": "Google Maps",
    "originURL": "https://www.google.com/maps/d/viewer?mid=11_PeKeHQmnFUU8PNuG_1yICZW5I&ll=35.662014%2C139.69897&z=17"
  },
  {
    "id": "4uicc0blt",
    "name": "ズドモンに進化した場所",
    "image": "https://image.xinu.ink/pic/data/115/images/4uicc0blt-1734788153443.jpg",
    "ep": 36,
    "geo": [
      35.6365,
      139.7653
    ],
    "origin": "Google Maps",
    "originURL": "https://www.google.com/maps/d/viewer?mid=11_PeKeHQmnFUU8PNuG_1yICZW5I&ll=35.636529%2C139.765395&z=17"
  },
  {
    "id": "4uicc0bkk",
    "name": "台場公園",
    "image": "https://image.xinu.ink/pic/data/115/images/4uicc0bkk-1734187226661.jpg",
    "ep": 34,
    "geo": [
      35.6331,
      139.7721
    ],
    "origin": "Google Maps",
    "originURL": "https://www.google.com/maps/d/viewer?mid=11_PeKeHQmnFUU8PNuG_1yICZW5I&ll=35.633163%2C139.772122&z=17"
  },
  {
    "id": "4uicc0bun",
    "name": "太一の住んでいるマンション",
    "image": "https://image.xinu.ink/pic/data/115/images/4uicc0bun-1734187250497.jpg",
    "ep": 31,
    "geo": [
      35.6305,
      139.7783
    ],
    "origin": "Google Maps",
    "originURL": "https://www.google.com/maps/d/viewer?mid=11_PeKeHQmnFUU8PNuG_1yICZW5I&ll=35.630582%2C139.778377&z=17"
  },
  {
    "id": "4uicc0bpm",
    "name": "シーリア前交差点",
    "image": "https://image.xinu.ink/pic/data/115/images/4uicc0bpm-1734790697711.jpg",
    "ep": 21,
    "geo": [
      35.631,
      139.7786
    ],
    "origin": "Google Maps",
    "originURL": "https://www.google.com/maps/d/viewer?mid=11_PeKeHQmnFUU8PNuG_1yICZW5I&ll=35.631066%2C139.778693&z=17"
  },
  {
    "id": "4uicc0bou",
    "name": "アクアシティお台場前",
    "image": "https://image.xinu.ink/pic/data/115/images/4uicc0bou-1734788330482.jpg",
    "ep": 36,
    "geo": [
      35.6274,
      139.7738
    ],
    "origin": "Google Maps",
    "originURL": "https://www.google.com/maps/d/viewer?mid=11_PeKeHQmnFUU8PNuG_1yICZW5I&ll=35.627434%2C139.773876&z=17"
  },
  {
    "id": "4uicc0brr",
    "name": "マルエツ",
    "image": "https://image.xinu.ink/pic/data/115/images/4uicc0brr-1734273130309.jpg",
    "ep": 31,
    "geo": [
      35.6297,
      139.7777
    ],
    "origin": "Google Maps",
    "originURL": "https://www.google.com/maps/d/viewer?mid=11_PeKeHQmnFUU8PNuG_1yICZW5I&ll=35.62976%2C139.777752&z=17"
  },
  {
    "id": "4uicc0c20",
    "name": "日の出水上バス",
    "image": "https://image.xinu.ink/pic/data/115/images/4uicc0c20-1734272588575.jpg",
    "ep": 35,
    "geo": [
      35.6508,
      139.7607
    ],
    "origin": "Google Maps",
    "originURL": "https://www.google.com/maps/d/viewer?mid=11_PeKeHQmnFUU8PNuG_1yICZW5I&ll=35.650854%2C139.760792&z=17"
  },
  {
    "id": "4uicc0ca2",
    "cn": "芝浦埠头",
    "name": "芝浦ふ頭",
    "image": "https://image.xinu.ink/pic/data/115/images/4uicc0ca2-1734187285580.jpg",
    "ep": 31,
    "geo": [
      35.642,
      139.758
    ],
    "origin": "Google Maps",
    "originURL": "https://www.google.com/maps/d/viewer?mid=11_PeKeHQmnFUU8PNuG_1yICZW5I&ll=35.642022%2C139.758067&z=17"
  },
  {
    "id": "p0k9m0vw5",
    "cn": "九龍公園 ",
    "name": "九龍公園 Kowloon Park",
    "image": "https://image.xinu.ink/pic/data/115/images/p0k9m0vw5-1728715201076.jpg",
    "ep": "Digimon Adventure 02 - Episode 40",
    "geo": [
      22.3004,
      114.1704
    ]
  },
  {
    "id": "qyelspjl9",
    "cn": "都营地下铁12号线 光丘站前",
    "name": "都営地下鉄12号線 光が丘駅前",
    "image": "https://image.xinu.ink/pic/data/115/images/qyelspjl9-1734188280534.jpg",
    "ep": 30,
    "geo": [
      35.7586,
      139.6285
    ]
  },
  {
    "id": "r632s9lf5",
    "name": "お台場海浜公園駅前バス停",
    "image": "https://image.xinu.ink/pic/data/115/images/r632s9lf5-1734790158319.jpg",
    "ep": 21,
    "geo": [
      35.6296,
      139.7785
    ]
  },
  {
    "id": "r78090o6p",
    "cn": "芝浦南埠头公园​运动广场",
    "name": "芝浦​南​ふ頭​公園​運動​広場",
    "image": "https://image.xinu.ink/pic/data/115/images/r78090o6p-1734879190400.jpg",
    "ep": 30,
    "geo": [
      35.637,
      139.7599
    ]
  },
  {
    "id": "4uicc0bej",
    "name": "光子郎の住んでるマンション",
    "image": "https://image.xinu.ink/pic/data/115/images/4uicc0bej-1734782006891.jpg",
    "ep": null,
    "geo": [
      35.6322,
      139.7784
    ],
    "origin": "Google Maps",
    "originURL": "https://www.google.com/maps/d/viewer?mid=11_PeKeHQmnFUU8PNuG_1yICZW5I&ll=35.632265%2C139.778457&z=17"
  },
  {
    "id": "4uicc0bta",
    "cn": "富士电视台",
    "name": "フジテレビ",
    "image": "https://image.xinu.ink/pic/data/115/images/4uicc0bta_1724821454994.jpg",
    "geo": [
      35.627,
      139.7745
    ],
    "origin": "Google Maps",
    "originURL": "https://www.google.com/maps/d/viewer?mid=11_PeKeHQmnFUU8PNuG_1yICZW5I&ll=35.627024%2C139.774579&z=17"
  },
  {
    "id": "4uicc0c28",
    "cn": "东京国际展览中心",
    "name": "ビックサイト正門付近",
    "image": "https://image.xinu.ink/pic/data/115/images/4uicc0c28-1724806838335.jpg",
    "ep": null,
    "geo": [
      35.6306,
      139.7929
    ],
    "origin": "Google Maps",
    "originURL": "https://www.google.com/maps/d/viewer?mid=11_PeKeHQmnFUU8PNuG_1yICZW5I&ll=35.630621%2C139.792909&z=17"
  },
  {
    "id": "4uicc0be5",
    "name": "大観覧車",
    "image": "https://image.xinu.ink/pic/data/115/images/4uicc0be5-1734785938578.jpg",
    "ep": null,
    "geo": [
      35.6263,
      139.7821
    ],
    "origin": "Google Maps",
    "originURL": "https://www.google.com/maps/d/viewer?mid=11_PeKeHQmnFUU8PNuG_1yICZW5I&ll=35.626331%2C139.782105&z=17"
  },
  {
    "id": "4uicc0bo3",
    "name": "空が歩いていた場所",
    "image": "https://image.xinu.ink/pic/data/115/images/4uicc0bo3-1734781861960.jpg",
    "ep": null,
    "geo": [
      35.6297,
      139.777
    ],
    "origin": "Google Maps",
    "originURL": "https://www.google.com/maps/d/viewer?mid=11_PeKeHQmnFUU8PNuG_1yICZW5I&ll=35.629771%2C139.777025&z=17"
  },
  {
    "id": "4uicc0cq6",
    "name": "ヒカリの友達の家",
    "image": "https://image.xinu.ink/pic/data/115/images/4uicc0cq6-1734782192086.jpg",
    "ep": null,
    "geo": [
      35.6316,
      139.7785
    ],
    "origin": "Google Maps",
    "originURL": "https://www.google.com/maps/d/viewer?mid=11_PeKeHQmnFUU8PNuG_1yICZW5I&ll=35.631672%2C139.778527&z=17"
  },
  {
    "id": "4uicc0ctn",
    "name": "ヒカリを背負っていたアグモンが見ていた病院看板前",
    "image": "https://image.xinu.ink/pic/data/115/images/4uicc0ctn.jpg",
    "geo": [
      35.7624,
      139.6303
    ],
    "origin": "Google Maps",
    "originURL": "https://www.google.com/maps/d/viewer?mid=11_PeKeHQmnFUU8PNuG_1yICZW5I&ll=35.762465%2C139.630351&z=17"
  },
  {
    "id": "4uicc0cnz",
    "name": "アグモンが壊した自動販売機",
    "image": "https://image.xinu.ink/pic/data/115/images/4uicc0cnz.jpg",
    "geo": [
      35.761,
      139.6292
    ],
    "origin": "Google Maps",
    "originURL": "https://www.google.com/maps/d/viewer?mid=11_PeKeHQmnFUU8PNuG_1yICZW5I&ll=35.761016%2C139.629292&z=17"
  },
  {
    "id": "4uicc0cqo",
    "name": "アグモンが見ていたアーチ状の通路",
    "image": "https://image.xinu.ink/pic/data/115/images/4uicc0cqo.jpg",
    "geo": [
      35.7603,
      139.6296
    ],
    "origin": "Google Maps",
    "originURL": "https://www.google.com/maps/d/viewer?mid=11_PeKeHQmnFUU8PNuG_1yICZW5I&ll=35.760385%2C139.629605&z=17"
  },
  {
    "id": "4uicc0cm1",
    "name": "アグモンがグレイモンに進化したところ（橋下横断歩道中）",
    "image": "https://image.xinu.ink/pic/data/115/images/4uicc0cm1.jpg",
    "geo": [
      35.7585,
      139.6293
    ],
    "origin": "Google Maps",
    "originURL": "https://www.google.com/maps/d/viewer?mid=11_PeKeHQmnFUU8PNuG_1yICZW5I&ll=35.758513%2C139.629359&z=17"
  },
  {
    "id": "4uicc0csk",
    "name": "コロモンが見つめていたゲート前",
    "image": "https://image.xinu.ink/pic/data/115/images/4uicc0csk.jpg",
    "geo": [
      35.7618,
      139.6305
    ],
    "origin": "Google Maps",
    "originURL": "https://www.google.com/maps/d/viewer?mid=11_PeKeHQmnFUU8PNuG_1yICZW5I&ll=35.761862%2C139.630501&z=17"
  },
  {
    "id": "4uicc0cll",
    "name": "アグモンが空を見つめていた場所",
    "image": "https://image.xinu.ink/pic/data/115/images/4uicc0cll.jpg",
    "geo": [
      35.7602,
      139.6293
    ],
    "origin": "Google Maps",
    "originURL": "https://www.google.com/maps/d/viewer?mid=11_PeKeHQmnFUU8PNuG_1yICZW5I&ll=35.760215%2C139.629328&z=17"
  },
  {
    "id": "4uicc0c63",
    "name": "ヒカリを探していた太一がヒカリを見つけた場所",
    "image": "https://image.xinu.ink/pic/data/115/images/4uicc0c63.jpg",
    "geo": [
      35.7586,
      139.6274
    ],
    "origin": "Google Maps",
    "originURL": "https://www.google.com/maps/d/viewer?mid=11_PeKeHQmnFUU8PNuG_1yICZW5I&ll=35.758693%2C139.627481&z=17"
  },
  {
    "id": "4uicc0cre",
    "name": "太一がヒカリを探して歩いていた歩道橋",
    "image": "https://image.xinu.ink/pic/data/115/images/4uicc0cre-1734781630959.jpg",
    "ep": null,
    "geo": [
      35.7605,
      139.6274
    ],
    "origin": "Google Maps",
    "originURL": "https://www.google.com/maps/d/viewer?mid=11_PeKeHQmnFUU8PNuG_1yICZW5I&ll=35.760525%2C139.627476&z=17"
  },
  {
    "id": "kfegfahce",
    "cn": "全家便利店台场海滨公园店",
    "name": "ファミリー​マート\nお台場​海浜​公園​店",
    "image": "https://image.xinu.ink/pic/data/115/images/kfegfahce-1715772428330.jpg",
    "ep": null,
    "geo": [
      35.6306,
      139.7787
    ]
  },
  {
    "id": "kfehxwhjp",
    "name": "シーリア​お台場​三番​街​4号棟",
    "image": "https://image.xinu.ink/pic/data/115/images/kfehxwhjp-1715772487967.jpg",
    "ep": null,
    "geo": [
      35.6314,
      139.7794
    ]
  },
  {
    "id": "qzl9k308t",
    "name": "横須賀線新橋駅",
    "image": "https://image.xinu.ink/pic/data/115/images/qzl9k308t_1734281145837.jpg",
    "geo": [
      35.6662,
      139.7586
    ],
    "origin": "Anitabi@月即别",
    "originURL": "https://anitabi.cn/"
  },
  {
    "id": "r61qum4yi",
    "name": "シーリア前信号",
    "image": "https://image.xinu.ink/pic/data/115/images/r61qum4yi-1734787282119.jpg",
    "ep": null,
    "geo": [
      35.6311,
      139.7786
    ]
  },
  {
    "id": "r61tstrfp",
    "cn": "台场海滨公园",
    "name": "お台場海浜公園",
    "image": "https://image.xinu.ink/pic/data/115/images/r61tstrfp-1734787372923.jpg",
    "ep": null,
    "geo": [
      35.6299,
      139.7787
    ]
  },
  {
    "id": "rqko4kz21",
    "name": "台场海滨公园码头",
    "image": "https://image.xinu.ink/pic/data/115/images/rqko4kz21-1736395708836.jpg",
    "ep": null,
    "geo": [
      35.6295,
      139.7747
    ]
  }
]